weblinx/__init__.py
weblinx/version.py
weblinx/_data/splits.json
weblinx/eval/__init__.py
weblinx/eval/__main__.py
weblinx/eval/metrics.py
weblinx/processing/__init__.py
weblinx/processing/dom.py
weblinx/processing/intent.py
weblinx/processing/outputs.py
weblinx/processing/prompt.py
weblinx/processing/truncation.py
weblinx/utils/__init__.py
weblinx/utils/envs.py
weblinx/utils/format.py
weblinx/utils/html.py
weblinx/utils/hydra.py
weblinx/utils/recs.py
weblinx/utils/url.py
weblinx/utils/video.py
weblinx-0.3.2.dist-info/LICENSE
weblinx-0.3.2.dist-info/METADATA
weblinx-0.3.2.dist-info/WHEEL
weblinx-0.3.2.dist-info/top_level.txt
weblinx-0.3.2.dist-info/RECORD
