Metadata-Version: 2.1
Name: weblinx
Version: 0.3.2
Summary: The official weblinx library
Home-page: https://github.com/McGill-NLP/weblinx
Author: McGill NLP
Author-email: weblinx@googlegroups.com
Classifier: Programming Language :: Python :: 3
Classifier: License :: OSI Approved :: Apache Software License
Classifier: Operating System :: OS Independent
Requires-Python: >=3.8
Provides-Extra: dev
Provides-Extra: video
Provides-Extra: processing
Provides-Extra: eval
Provides-Extra: all
License-File: LICENSE
